pyscriptbase/__init__.py
pyscriptbase/app.py
pyscriptbase/cipher.py
pyscriptbase/database.py
pyscriptbase/env.py
pyscriptbase/net.py
pyscriptbase/panel.py
pyscriptbase/pusher.py
pyscriptbase/script.py
pyscriptbase/util.py
pyscriptbase/webview.py
pyscriptbase-1.1.1.dist-info/METADATA
pyscriptbase-1.1.1.dist-info/WHEEL
pyscriptbase-1.1.1.dist-info/top_level.txt
pyscriptbase-1.1.1.dist-info/RECORD
