Metadata-Version: 2.4
Name: pyscriptbase
Version: 1.1.1
Summary: python script base library
Home-page: 
Author: ASMan
Author-email: 
Requires-Dist: loguru
Requires-Dist: selenium
Requires-Dist: pymysql
Requires-Dist: pycryptodome
Requires-Dist: pyyaml
Requires-Dist: xmltodict
Requires-Dist: prettytable
Requires-Dist: pyjwt
Requires-Dist: fake_useragent
Requires-Dist: beautifulsoup4
Requires-Dist: requests
Requires-Dist: lxml
Requires-Dist: brotli
Dynamic: author
Dynamic: description
Dynamic: description-content-type
Dynamic: requires-dist
Dynamic: summary
